atmos_phys/__init__.py
atmos_phys/convert/__init__.py
atmos_phys/convert/aerosol.py
atmos_phys/convert/base.py
atmos_phys/convert/electric.py
atmos_phys/convert/elements.py
atmos_phys/convert/gas.py
atmos_phys/convert/precipitation.py
atmos_phys/convert/pressure.py
atmos_phys/convert/temperature.py
databases/__init__.py
databases/base.py
databases/postgres.py
databases/sqlite.py
ebas/__init__.py
ebas/commandline.py
ebas/db_fileindex/__init__.py
ebas/db_fileindex/indexdb.py
ebas/db_fileindex/indexdb_internal.py
ebas/domain/__init__.py
ebas/domain/base.py
ebas/domain/basic_domain_logic/__init__.py
ebas/domain/basic_domain_logic/base.py
ebas/domain/basic_domain_logic/datalevel.py
ebas/domain/basic_domain_logic/dataset_types.py
ebas/domain/basic_domain_logic/export_filter.py
ebas/domain/basic_domain_logic/flags.py
ebas/domain/basic_domain_logic/parameters.py
ebas/domain/basic_domain_logic/time_period.py
ebas/domain/basic_domain_logic/unit_convert.py
ebas/domain/basic_domain_logic/value_check.py
ebas/domain/masterdata/__init__.py
ebas/domain/masterdata/ac.py
ebas/domain/masterdata/am.py
ebas/domain/masterdata/ax.py
ebas/domain/masterdata/ay.py
ebas/domain/masterdata/base.py
ebas/domain/masterdata/bc.py
ebas/domain/masterdata/ca.py
ebas/domain/masterdata/cc.py
ebas/domain/masterdata/co.py
ebas/domain/masterdata/cy.py
ebas/domain/masterdata/dc.py
ebas/domain/masterdata/dl.py
ebas/domain/masterdata/fl.py
ebas/domain/masterdata/fm.py
ebas/domain/masterdata/fp.py
ebas/domain/masterdata/ft.py
ebas/domain/masterdata/ht.py
ebas/domain/masterdata/im.py
ebas/domain/masterdata/ip.py
ebas/domain/masterdata/it.py
ebas/domain/masterdata/ma.py
ebas/domain/masterdata/md.py
ebas/domain/masterdata/oc.py
ebas/domain/masterdata/org.py
ebas/domain/masterdata/pg_pl.py
ebas/domain/masterdata/pm.py
ebas/domain/masterdata/pr.py
ebas/domain/masterdata/ps.py
ebas/domain/masterdata/qm_qv.py
ebas/domain/masterdata/re.py
ebas/domain/masterdata/sc.py
ebas/domain/masterdata/se.py
ebas_io-4.5.3.dist-info/licenses/LICENSE
ebas_io-4.5.3.dist-info/METADATA
ebas_io-4.5.3.dist-info/WHEEL
ebas_io-4.5.3.dist-info/top_level.txt
ebas_io-4.5.3.dist-info/RECORD
