Metadata-Version: 2.4
Name: ebas-io
Version: 4.5.3
Summary: EBAS file I/O
Author: Paul Eckhardt, NILU
Author-email: Paul Eckhardt <pe@nilu.no>
License-Expression: AGPL-3.0-only
Project-URL: Homepage, https://git.nilu.no/ebas/ebas-io/-/wikis/home
Project-URL: Issues, https://git.nilu.no/ebas/ebas-io/-/issues
Classifier: Programming Language :: Python :: 3
Classifier: Operating System :: OS Independent
Requires-Python: >=3.8
License-File: LICENSE
Requires-Dist: python-dateutil
Requires-Dist: datadiff
Dynamic: author
Dynamic: license-file
